[
    {
      "id": "1111",
      "name": "John Doe",
      "email": "john.doe@example.com",
      "about": "Software Engineer"
    },
    {
      "id": "2222",
      "name": "Jane Smith",
      "email": "jane.smith@example.com",
      "about": "Data Scientist"
    },
    {
      "id": "3333",
      "name": "Robert Jones",
      "email": "robert.jones@example.com",
      "about": "Web Developer"
    },
    {
      "id": "4444",
      "name": "Alice Brown",
      "email": "alice.brown@example.com",
      "about": "Project Manager"
    },
      {
      "id": "5555",
      "name": "Bob Williams",
      "email": "bob.williams@example.com",
      "about": "Software Tester"
    }
  ]
  